{
    "version": "0.8.0",
    "architecture": {
        "64bit": {
            "url": "https://github.com/matcra587/jira-cli/releases/download/v0.8.0/jira_0.8.0_windows_amd64.zip",
            "bin": [
                "jira.exe"
            ],
            "hash": "e9d47a517fec0915f22ebf569e96db92a5564aa7178191d63488fa4dd44c71e3"
        },
        "arm64": {
            "url": "https://github.com/matcra587/jira-cli/releases/download/v0.8.0/jira_0.8.0_windows_arm64.zip",
            "bin": [
                "jira.exe"
            ],
            "hash": "655a38c63e0a46b4a32d491744d49d927aae2e11c9520978c2d2f25771afa829"
        }
    },
    "homepage": "https://github.com/matcra587/jira-cli",
    "license": "MIT",
    "description": "Agent-first Jira CLI for developer workflows"
}
